{"random": "\n    public static String random(int count) {\n        return random(count, false, false);\n    }", "randomAscii": "\n    public static String randomAscii(int count) {\n        return random(count, 32, 127, false, false);\n    }", "randomAlphabetic": "\n    public static String randomAlphabetic(int count) {\n        return random(count, true, false);\n    }", "randomAlphanumeric": "\n    public static String randomAlphanumeric(int count) {\n        return random(count, true, true);\n    }", "randomNumeric": "\n    public static String randomNumeric(int count) {\n        return random(count, false, true);\n    }"}